## Java 바이트코드의 4가지 특징 상세 설명

### 1. **플랫폼 독립적 (Platform Independent)**

**핵심 개념**: "Write Once, Run Anywhere" (WORA)

```java
// HelloWorld.java
public class HelloWorld {
    public static void main(String[] args) {
        System.out.println("Hello, World!");
    }
}
```

**작동 원리**:
- **컴파일 단계**: `javac HelloWorld.java` → `HelloWorld.class` (바이트코드)
- **실행 단계**: 각 플랫폼의 JVM이 바이트코드를 해당 OS의 기계어로 변환

**플랫폼 독립성의 실현**:
```
Windows JVM → Windows 기계어
Linux JVM   → Linux 기계어
MacOS JVM   → MacOS 기계어
```

**장점**:
- 개발자는 OS별로 다른 코드를 작성할 필요 없음
- 배포가 간편함 (하나의 .jar 파일로 모든 플랫폼 지원)
- 유지보수 비용 절감

### 2. **스택 기반 명령어 (Stack-based Instructions)**

**스택 기반 vs 레지스터 기반**:

```java
// Java 코드
int result = a + b;

// 바이트코드 (스택 기반)
iload_1      // 변수 a를 스택에 push
iload_2      // 변수 b를 스택에 push
iadd         // 스택에서 두 값을 pop하고 더한 후 결과를 push
istore_3     // 스택에서 pop하여 result에 저장

// x86 어셈블리 (레지스터 기반)
mov eax, [a]    // a를 eax 레지스터에 로드
add eax, [b]    // b를 eax에 더함
mov [result], eax // 결과를 메모리에 저장
```

**스택 기반의 특징**:
- **단순한 명령어 구조**: 대부분의 연산이 스택 top에서 수행
- **레지스터 할당 불필요**: 컴파일러 구현이 간단
- **명령어 수는 많지만 각 명령어는 단순**
- **메모리 접근 패턴이 예측 가능**

**실제 바이트코드 예시**:
```java
public int calculate(int x, int y) {
    return x * 2 + y;
}

// 바이트코드
0: iload_1       // x를 스택에 push
1: iconst_2      // 상수 2를 스택에 push
2: imul          // 곱셈 (x * 2)
3: iload_2       // y를 스택에 push
4: iadd          // 덧셈 (x*2 + y)
5: ireturn       // 결과 반환
```

### 3. **클래스 파일(.class)에 저장**

**클래스 파일 구조**:
```
ClassFile {
    u4             magic;              // 0xCAFEBABE
    u2             minor_version;      // 부 버전
    u2             major_version;      // 주 버전
    u2             constant_pool_count;// 상수 풀 크기
    cp_info        constant_pool[];    // 상수 풀
    u2             access_flags;       // 접근 제어자
    u2             this_class;         // 현재 클래스
    u2             super_class;        // 부모 클래스
    u2             interfaces_count;   // 인터페이스 수
    u2             interfaces[];       // 인터페이스들
    u2             fields_count;       // 필드 수
    field_info     fields[];          // 필드들
    u2             methods_count;      // 메서드 수
    method_info    methods[];         // 메서드들
    u2             attributes_count;   // 속성 수
    attribute_info attributes[];      // 속성들
}
```

**주요 섹션 설명**:
- **Magic Number (0xCAFEBABE)**: 클래스 파일 식별자
- **상수 풀**: 문자열, 숫자, 클래스/메서드 참조 등 저장
- **메서드 정보**: 각 메서드의 바이트코드 포함
- **속성 정보**: 디버깅 정보, 애노테이션 등

**javap로 클래스 파일 분석**:
```bash
javap -v HelloWorld.class

Classfile HelloWorld.class
  Last modified 2024-01-01; size 425 bytes
  MD5 checksum 3a5f1c2d4e6f7a8b9c0d1e2f3a4b5c6d
  Compiled from "HelloWorld.java"
public class HelloWorld
  minor version: 0
  major version: 55  // Java 11
  flags: ACC_PUBLIC, ACC_SUPER
Constant pool:
   #1 = Methodref          #6.#15
   #2 = Fieldref           #16.#17
   #3 = String             #18
   ...
```

### 4. **실제 기계어보다 추상화 수준이 높음**

**추상화 수준 비교**:

```java
// Java 소스 코드 (최고 수준 추상화)
List<String> names = new ArrayList<>();
names.add("Alice");

// 바이트코드 (중간 수준 추상화)
0: new           #2  // class java/util/ArrayList
3: dup
4: invokespecial #3  // Method java/util/ArrayList."<init>":()V
7: astore_1
8: aload_1
9: ldc           #4  // String Alice
11: invokeinterface #5,  2  // InterfaceMethod java/util/List.add:(Ljava/lang/Object;)Z

// x86 기계어 (최저 수준 추상화)
48 89 e5    ; mov rbp, rsp
48 83 ec 10 ; sub rsp, 0x10
48 8b 3d... ; mov rdi, [rip+...]
e8 xx xx... ; call malloc
48 89 45 f8 ; mov [rbp-8], rax
...
```

**높은 추상화 수준의 장점**:

1. **객체 지향 개념 보존**:
   - 클래스, 인터페이스, 상속 관계가 바이트코드에 그대로 유지
   - 메서드 호출이 `invokevirtual`, `invokeinterface` 등으로 표현

2. **타입 안전성**:
   ```
   iload   // int 로드
   fload   // float 로드
   aload   // 객체 참조 로드
   ```

3. **메모리 관리 추상화**:
   - 가비지 컬렉션 지원
   - 명시적 메모리 할당/해제 불필요

4. **보안 검증 가능**:
   - 바이트코드 검증기가 타입 안전성, 스택 오버플로우 등을 검사
   - 악의적인 코드 실행 방지

**실제 차이점 예시**:
```java
// Java: 예외 처리가 언어 수준에서 지원
try {
    riskyOperation();
} catch (Exception e) {
    handleError(e);
}

// 바이트코드: 예외 테이블로 표현
Exception table:
   from    to  target type
     0     5     8   Class java/lang/Exception

// 기계어: 예외 처리를 위한 복잡한 스택 풀기 코드 필요
```

이러한 추상화 덕분에 JVM은 런타임에 다양한 최적화를 수행할 수 있으며, 플랫폼별 최적화도 가능합니다.